accelbyte_py_sdk/__init__.py
accelbyte_py_sdk/__main__.py
accelbyte_py_sdk/api/__init__.py
accelbyte_py_sdk/core/__init__.py
accelbyte_py_sdk/core/_api_response.py
accelbyte_py_sdk/core/_config_repository.py
accelbyte_py_sdk/core/_core.py
accelbyte_py_sdk/core/_decorators.py
accelbyte_py_sdk/core/_flight_id.py
accelbyte_py_sdk/core/_header.py
accelbyte_py_sdk/core/_headerstr.py
accelbyte_py_sdk/core/_http_backoff_policy.py
accelbyte_py_sdk/core/_http_client.py
accelbyte_py_sdk/core/_http_response.py
accelbyte_py_sdk/core/_http_retry_policy.py
accelbyte_py_sdk/core/_http_status_codes.py
accelbyte_py_sdk/core/_http_utils.py
accelbyte_py_sdk/core/_meta_classes.py
accelbyte_py_sdk/core/_model.py
accelbyte_py_sdk/core/_operation.py
accelbyte_py_sdk/core/_proto_http_request.py
accelbyte_py_sdk/core/_sdk.py
accelbyte_py_sdk/core/_strenum.py
accelbyte_py_sdk/core/_timer.py
accelbyte_py_sdk/core/_token_repository.py
accelbyte_py_sdk/core/_utils.py
accelbyte_py_sdk/core/_validators.py
accelbyte_py_sdk/core/_websocket_client.py
accelbyte_py_sdk/core/_ws_client.py
accelbyte_py_sdk/core/_wsm.py
accelbyte_py_sdk/services/__init__.py
accelbyte_py_sdk_core-0.9.0.dist-info/METADATA
accelbyte_py_sdk_core-0.9.0.dist-info/WHEEL
accelbyte_py_sdk_core-0.9.0.dist-info/top_level.txt
accelbyte_py_sdk_core-0.9.0.dist-info/RECORD
