Metadata-Version: 2.4
Name: accelbyte-py-sdk-core
Version: 0.9.0
Summary: AccelByte Python SDK - Core
Requires-Python: >=3.9
Requires-Dist: bitarray
Requires-Dist: httpx
Requires-Dist: mmh3
Requires-Dist: PyJWT[crypto]
Requires-Dist: PyYAML
Requires-Dist: requests
Requires-Dist: websockets
